J1939_PGN/J1939_PGN.py
J1939_PGN/__init__.py
J1939_PGN/_version.py
J1939_PGN-0.4.dist-info/LICENSE
J1939_PGN-0.4.dist-info/METADATA
J1939_PGN-0.4.dist-info/WHEEL
J1939_PGN-0.4.dist-info/top_level.txt
J1939_PGN-0.4.dist-info/RECORD
