Metadata-Version: 2.1
Name: J1939-PGN
Version: 0.4
Summary: Python module for working with SAE J1939 PGNs
Home-page: https://github.com/CSS-Electronics/j1939/
Author: Christian Steiniche
Author-email: css@csselectronics.com
License: LICENSE
Platform: UNKNOWN
